{
  "data": {
    "Solana": {
      "DEXTrades": [
        {
          "Block": {
            "Time": "2024-12-20T15:24:47Z"
          },
          "Trade": {
            "Buy": {
              "Currency": {
                "Uri": "https://ipfs.io/ipfs/QmdTyJD2Na9CRh29kes5wCPN56kKb3Ki3qQXcCcjudXQXv"
              },
              "Price": 2.0166028099274954e-7,
              "PriceInUSD": 0.00003835733876070605
            }
          }
        },
        {
          "Block": {
            "Time": "2024-12-20T15:24:47Z"
          },
          "Trade": {
            "Buy": {
              "Currency": {
                "Uri": "https://ipfs.io/ipfs/QmTHR7WWEhCzQTJgbUq6vegAJ5KpBvuZrnWGfJZ6RRhvpB"
              },
              "Price": 5.446188938988971e-8,
              "PriceInUSD": 0.00001035907086210601
            }
          }
        },
        {
          "Block": {
            "Time": "2024-12-20T15:24:47Z"
          },
          "Trade": {
            "Buy": {
              "Currency": {
                "Uri": "https://cf-ipfs.com/ipfs/QmYTdQGxKLF4agw8vApEfhMdo7T8nnzsJnBAYBNWZB4eoZ"
              },
              "Price": 2.823817322145091e-8,
              "PriceInUSD": 0.000005371118055109889
            }
          }
        },
        {
          "Block": {
            "Time": "2024-12-20T15:24:47Z"
          },
          "Trade": {
            "Buy": {
              "Currency": {
                "Uri": "https://ipfs.io/ipfs/QmSBqtKSzKVJAqGu4DY9JncUYa1ZeD6Nr3deCq4hXhfs5u"
              },
              "Price": 4.10541379327642e-8,
              "PriceInUSD": 0.00000780881325992205
            }
          }
        },
        {
          "Block": {
            "Time": "2024-12-20T15:24:47Z"
          },
          "Trade": {
            "Buy": {
              "Currency": {
                "Uri": "https://ipfs.io/ipfs/QmPhrKDWyzCqDH7wcMQUrVPb1gsD3Z6X2WeLdnJ6oTyDhd"
              },
              "Price": 3.8010505e-8,
              "PriceInUSD": 0.000007229890832111511
            }
          }
        },
        {
          "Block": {
            "Time": "2024-12-20T15:24:47Z"
          },
          "Trade": {
            "Buy": {
              "Currency": {
                "Uri": "https://ipfs.io/ipfs/QmQyF3VrMp4NRfQThNkdtyhZcJqkuvgZZ25Estmay8LtZS"
              },
              "Price": 1.0929534343689147e-7,
              "PriceInUSD": 0.000020788816184022303
            }
          }
        },
        {
          "Block": {
            "Time": "2024-12-20T15:24:47Z"
          },
          "Trade": {
            "Buy": {
              "Currency": {
                "Uri": "https://ipfs.io/ipfs/QmcuA3MnYrr4RXCM6YHmE7y6CCVXDXQEMfwtnbECG94KHD"
              },
              "Price": 1.488137635800829e-7,
              "PriceInUSD": 0.000028305524091291376
            }
          }
        },
        {
          "Block": {
            "Time": "2024-12-20T15:24:47Z"
          },
          "Trade": {
            "Buy": {
              "Currency": {
                "Uri": "https://ipfs.io/ipfs/QmWtpxbtXEEdo6KvVpnmB6zxx6BznaLjQruCZABH3JJ6xE"
              },
              "Price": 2.9822926374650956e-8,
              "PriceInUSD": 0.000005672550311626366
            }
          }
        },
        {
          "Block": {
            "Time": "2024-12-20T15:24:46Z"
          },
          "Trade": {
            "Buy": {
              "Currency": {
                "Uri": "https://ipfs.io/ipfs/Qmcy7p2uyKbMEQy5pkcVGEKVTvMTjijTLNMGKvwsJb49Xu"
              },
              "Price": 6.398183835361715e-8,
              "PriceInUSD": 0.000012169838483715417
            }
          }
        },
        {
          "Block": {
            "Time": "2024-12-20T15:24:46Z"
          },
          "Trade": {
            "Buy": {
              "Currency": {
                "Uri": "https://ipfs.io/ipfs/QmRE8gCvVp7YZ6zdcr2q54RdX6o9G5CX14aRKdGHWj2A4h"
              },
              "Price": 2.6642827173816736e-7,
              "PriceInUSD": 0.000050676709484788235
            }
          }
        },
        {
          "Block": {
            "Time": "2024-12-20T15:24:46Z"
          },
          "Trade": {
            "Buy": {
              "Currency": {
                "Uri": "https://ipfs.io/ipfs/Qmf3toNt3nGMmpNzhNDsGnucZuWE2cWfBp47g9EgyuQBRE"
              },
              "Price": 2.069840931291672e-7,
              "PriceInUSD": 0.000039369968836443534
            }
          }
        },
        {
          "Block": {
            "Time": "2024-12-20T15:24:46Z"
          },
          "Trade": {
            "Buy": {
              "Currency": {
                "Uri": "https://ipfs.io/ipfs/QmYbmZ5HmhGno1vHvxCj8zGgiduTuSbnrarYF6ZJtnZesE"
              },
              "Price": 3.47690724219327e-8,
              "PriceInUSD": 0.000006613345388185514
            }
          }
        },
        {
          "Block": {
            "Time": "2024-12-20T15:24:46Z"
          },
          "Trade": {
            "Buy": {
              "Currency": {
                "Uri": "https://ipfs.io/ipfs/QmYb3eycr6at1k1YmPmsuSAMYadeP6eXuq1iHQESuvNJDr"
              },
              "Price": 2.0085039736260558e-7,
              "PriceInUSD": 0.00003820329265601328
            }
          }
        },
        {
          "Block": {
            "Time": "2024-12-20T15:24:46Z"
          },
          "Trade": {
            "Buy": {
              "Currency": {
                "Uri": "https://ipfs.io/ipfs/QmXkiU6znpgteD1PUkrPPA9JUHdw69jd2eTagQnVQ2ucFC"
              },
              "Price": 2.7993970836798198e-8,
              "PriceInUSD": 0.000005324668880546688
            }
          }
        },
        {
          "Block": {
            "Time": "2024-12-20T15:24:45Z"
          },
          "Trade": {
            "Buy": {
              "Currency": {
                "Uri": "https://ipfs.io/ipfs/QmcH3bJSvjLT2NxqFtTPoMN8qcDpXJtVHWAKsHnAkJkuNB"
              },
              "Price": 4.145239684803035e-8,
              "PriceInUSD": 0.000007884565173249414
            }
          }
        },
        {
          "Block": {
            "Time": "2024-12-20T15:24:45Z"
          },
          "Trade": {
            "Buy": {
              "Currency": {
                "Uri": "https://ipfs.io/ipfs/QmS4EhQs9kTqXd7neW3XyrU8NFdxxwoD9g8Gu1DmRKcbme"
              },
              "Price": 8.311300090289068e-8,
              "PriceInUSD": 0.000015808732960982366
            }
          }
        },
        {
          "Block": {
            "Time": "2024-12-20T15:24:45Z"
          },
          "Trade": {
            "Buy": {
              "Currency": {
                "Uri": "https://ipfs.io/ipfs/QmWT2H3p6tktAHP3jxJE3sZWu7wNNFvwHLQJiixqizrJBg"
              },
              "Price": 9.350508119327683e-8,
              "PriceInUSD": 0.000017785386678633042
            }
          }
        },
        {
          "Block": {
            "Time": "2024-12-20T15:24:45Z"
          },
          "Trade": {
            "Buy": {
              "Currency": {
                "Uri": "https://ipfs.io/ipfs/Qmcbauh3FtWLP23EssqDNuMo1rhTAFBNvzymKERaRqj71A"
              },
              "Price": 2.8752911358363723e-8,
              "PriceInUSD": 0.00000546902521359158
            }
          }
        },
        {
          "Block": {
            "Time": "2024-12-20T15:24:45Z"
          },
          "Trade": {
            "Buy": {
              "Currency": {
                "Uri": "https://ipfs.io/ipfs/QmXy3dx8E3M3Y497vDBSGwymRSHSXL9Bme9cDMwhvhPX6q"
              },
              "Price": 2.803314700138831e-8,
              "PriceInUSD": 0.000005332120488811491
            }
          }
        },
        {
          "Block": {
            "Time": "2024-12-20T15:24:45Z"
          },
          "Trade": {
            "Buy": {
              "Currency": {
                "Uri": "https://ipfs.io/ipfs/QmcXn5NS7zkk3WnQosTK9h1Fw2XHQLv48hnraza6KbKYsC"
              },
              "Price": 1.2375888867435054e-7,
              "PriceInUSD": 0.00002353989389562165
            }
          }
        },
        {
          "Block": {
            "Time": "2024-12-20T15:24:45Z"
          },
          "Trade": {
            "Buy": {
              "Currency": {
                "Uri": "https://ipfs.io/ipfs/Qmcx15JNyr3bKRMmAtaFET5VK8tHpHgJjGDwM8wgVGt7BC"
              },
              "Price": 2.574433907855586e-7,
              "PriceInUSD": 0.00004896771592032811
            }
          }
        },
        {
          "Block": {
            "Time": "2024-12-20T15:24:45Z"
          },
          "Trade": {
            "Buy": {
              "Currency": {
                "Uri": "https://ipfs.io/ipfs/QmekMB48u9w6rjShvgkydCp313sYuXZaUyrqDrJ9gS7aHM"
              },
              "Price": 5.149621127201028e-8,
              "PriceInUSD": 0.000009794976040544175
            }
          }
        },
        {
          "Block": {
            "Time": "2024-12-20T15:24:45Z"
          },
          "Trade": {
            "Buy": {
              "Currency": {
                "Uri": "https://ipfs.io/ipfs/QmeQZFsawqXAt2HVfeKP9e9MQfYN66scMNqguyVJUZYbTV"
              },
              "Price": 2.7968313140800672e-8,
              "PriceInUSD": 0.000005319788589136047
            }
          }
        },
        {
          "Block": {
            "Time": "2024-12-20T15:24:45Z"
          },
          "Trade": {
            "Buy": {
              "Currency": {
                "Uri": "https://ipfs.io/ipfs/QmUpUK4gAchCQE8wUpULbWJnLqfRkp34M52ern6hfxhnJp"
              },
              "Price": 4.268666875480038e-8,
              "PriceInUSD": 0.000008119333197065184
            }
          }
        },
        {
          "Block": {
            "Time": "2024-12-20T15:24:45Z"
          },
          "Trade": {
            "Buy": {
              "Currency": {
                "Uri": "https://ipfs.io/ipfs/QmfVe8cJMgZaKA7jqzLB1GmC6i6z3oDVaUCQnYhNncBaQS"
              },
              "Price": 2.5623121980653793e-7,
              "PriceInUSD": 0.00004873715166320569
            }
          }
        },
        {
          "Block": {
            "Time": "2024-12-20T15:24:45Z"
          },
          "Trade": {
            "Buy": {
              "Currency": {
                "Uri": "https://ipfs.io/ipfs/QmW2GrrAM2gCT2eTe2TVAACLFt7yuovSRfM7by4Shg9W8g"
              },
              "Price": 4.969536785203417e-8,
              "PriceInUSD": 0.000009452441750822068
            }
          }
        },
        {
          "Block": {
            "Time": "2024-12-20T15:24:45Z"
          },
          "Trade": {
            "Buy": {
              "Currency": {
                "Uri": "https://ipfs.io/ipfs/QmPekpK2o95dFtJdKq46Rf1wyUcLdjuf7UwnwuAQVq4hfn"
              },
              "Price": 3.700171262638368e-8,
              "PriceInUSD": 0.000007038010752288509
            }
          }
        },
        {
          "Block": {
            "Time": "2024-12-20T15:24:45Z"
          },
          "Trade": {
            "Buy": {
              "Currency": {
                "Uri": "https://ipfs.io/ipfs/QmZoRiRfGEAommLjd1VKZVkdxYYGMT8xtmypWzwuKosBg3"
              },
              "Price": 3.0061409688288426e-8,
              "PriceInUSD": 0.000005717911674830541
            }
          }
        },
        {
          "Block": {
            "Time": "2024-12-20T15:24:44Z"
          },
          "Trade": {
            "Buy": {
              "Currency": {
                "Uri": "https://ipfs.io/ipfs/QmUFY7YSKWea4awKza72Am1ScbPLKvfYbkrNA9eugLmNQW"
              },
              "Price": 3.5747622547464287e-7,
              "PriceInUSD": 0.00006799473159477749
            }
          }
        },
        {
          "Block": {
            "Time": "2024-12-20T15:24:43Z"
          },
          "Trade": {
            "Buy": {
              "Currency": {
                "Uri": "https://ipfs.io/ipfs/QmSgwYJRdKNXjav4FgthjHbCgamQFSKeWBJp2MfewKFgxC"
              },
              "Price": 7.517283202005657e-8,
              "PriceInUSD": 0.00001429845167923093
            }
          }
        },
        {
          "Block": {
            "Time": "2024-12-20T15:24:43Z"
          },
          "Trade": {
            "Buy": {
              "Currency": {
                "Uri": "https://ipfs.io/ipfs/QmRJd3ELYiWjSmnLrj3XTDbGUkCbqiYQ8d8aMy8hoCavdo"
              },
              "Price": 4.3485447359902826e-8,
              "PriceInUSD": 0.000008271267040457083
            }
          }
        },
        {
          "Block": {
            "Time": "2024-12-20T15:24:43Z"
          },
          "Trade": {
            "Buy": {
              "Currency": {
                "Uri": "https://ipfs.io/ipfs/QmX93MaCmnDb7QGSMBW4BwSx5bAcUMnjZCN8Cp11mWV4QH"
              },
              "Price": 7.454145980392907e-8,
              "PriceInUSD": 0.000014178359820492665
            }
          }
        },
        {
          "Block": {
            "Time": "2024-12-20T15:24:43Z"
          },
          "Trade": {
            "Buy": {
              "Currency": {
                "Uri": "https://ipfs.io/ipfs/QmePYi6fx47xk6P6MyEzuJanSg67uN1x7fnDwPnaYM1VUi"
              },
              "Price": 3.13047130286154e-7,
              "PriceInUSD": 0.00005954397546874694
            }
          }
        },
        {
          "Block": {
            "Time": "2024-12-20T15:24:43Z"
          },
          "Trade": {
            "Buy": {
              "Currency": {
                "Uri": "https://ipfs.io/ipfs/Qmbg2XunFDhi3ZVN8PeznW9zYVdtsUvSa2eJjyon1CL1vf"
              },
              "Price": 2.8566616473474176e-8,
              "PriceInUSD": 0.000005433590491523767
            }
          }
        },
        {
          "Block": {
            "Time": "2024-12-20T15:24:43Z"
          },
          "Trade": {
            "Buy": {
              "Currency": {
                "Uri": "https://ipfs.io/ipfs/QmNg3TbdawkYETHB2zQ81sWoZ1kLRkcuT1pvpXRwnkYw1a"
              },
              "Price": 5.7727295954422116e-8,
              "PriceInUSD": 0.000010980176342920579
            }
          }
        },
        {
          "Block": {
            "Time": "2024-12-20T15:24:43Z"
          },
          "Trade": {
            "Buy": {
              "Currency": {
                "Uri": "https://ipfs.io/ipfs/QmUSPBvbV29eBrAmVoGo7iTG1ZDorvd7XCiBLxtNkJ79Mq"
              },
              "Price": 3.323596115105416e-8,
              "PriceInUSD": 0.000006321735815465247
            }
          }
        },
        {
          "Block": {
            "Time": "2024-12-20T15:24:43Z"
          },
          "Trade": {
            "Buy": {
              "Currency": {
                "Uri": "https://ipfs.io/ipfs/QmNr8tPiKzwx13oPRoBfPnFVc2he9FoaipAnPtj5oxjVaf"
              },
              "Price": 2.0583821917174265e-7,
              "PriceInUSD": 0.00003915201478349057
            }
          }
        },
        {
          "Block": {
            "Time": "2024-12-20T15:24:43Z"
          },
          "Trade": {
            "Buy": {
              "Currency": {
                "Uri": "https://cf-ipfs.com/ipfs/QmRg5ADhFv2HMX7RGLnFWPjS1GGbkPLFg1JLqftGrE6thp"
              },
              "Price": 1.327437026840981e-7,
              "PriceInUSD": 0.000025248874727033936
            }
          }
        },
        {
          "Block": {
            "Time": "2024-12-20T15:24:43Z"
          },
          "Trade": {
            "Buy": {
              "Currency": {
                "Uri": "https://ipfs.io/ipfs/QmP2zg9Dz7Bmv84LxfB9FcN1gHWwGKFaH8UpZ8U71Jaxfm"
              },
              "Price": 4.7715052271259685e-8,
              "PriceInUSD": 0.000009075770473707253
            }
          }
        },
        {
          "Block": {
            "Time": "2024-12-20T15:24:43Z"
          },
          "Trade": {
            "Buy": {
              "Currency": {
                "Uri": "https://ipfs.io/ipfs/QmZNcDPpsb7VTE8QSq7YBbgarxFs3k6kMPhrhVxrScNaQS"
              },
              "Price": 3.263412235762633e-8,
              "PriceInUSD": 0.000006207261441209684
            }
          }
        },
        {
          "Block": {
            "Time": "2024-12-20T15:24:43Z"
          },
          "Trade": {
            "Buy": {
              "Currency": {
                "Uri": "https://ipfs.io/ipfs/QmUZAViS5nwwKLpeqAfHcsL9rL9WG7RbjKPoxz9t98Kcpi"
              },
              "Price": 2.0031324769428477e-7,
              "PriceInUSD": 0.00003810112265162991
            }
          }
        },
        {
          "Block": {
            "Time": "2024-12-20T15:24:43Z"
          },
          "Trade": {
            "Buy": {
              "Currency": {
                "Uri": "https://ipfs.io/ipfs/QmWYE4h1gEsUBkvw64aBLdGENWrhZEykFFrrKzscAhQYaP"
              },
              "Price": 2.801964594704465e-8,
              "PriceInUSD": 0.00000532955248428161
            }
          }
        },
        {
          "Block": {
            "Time": "2024-12-20T15:24:43Z"
          },
          "Trade": {
            "Buy": {
              "Currency": {
                "Uri": "https://ipfs.io/ipfs/QmRjJfMAvLwWEXSXQwFHqPTDFh2WPbzXr9vdJrv6Javbmr"
              },
              "Price": 6.265466084063524e-8,
              "PriceInUSD": 0.000011917399097980014
            }
          }
        },
        {
          "Block": {
            "Time": "2024-12-20T15:24:43Z"
          },
          "Trade": {
            "Buy": {
              "Currency": {
                "Uri": "https://ipfs.io/ipfs/QmSrSaY1stEZh8gsCjWV3sdkqvosz8FgseruUTbCMfbMqF"
              },
              "Price": 1.2407267660721933e-7,
              "PriceInUSD": 0.000023599578777447744
            }
          }
        },
        {
          "Block": {
            "Time": "2024-12-20T15:24:43Z"
          },
          "Trade": {
            "Buy": {
              "Currency": {
                "Uri": "https://ipfs.io/ipfs/QmZhijpm1sm8iQjTf4caeVTyAQ241BYRNGwgF95KNiprSp"
              },
              "Price": 7.104590281629387e-8,
              "PriceInUSD": 0.000013513477956438844
            }
          }
        },
        {
          "Block": {
            "Time": "2024-12-20T15:24:43Z"
          },
          "Trade": {
            "Buy": {
              "Currency": {
                "Uri": "https://ipfs.io/ipfs/QmVYGRvEcnLdZsHwMCei7BUFfVu1MtS5U5JGJRZHBNLKso"
              },
              "Price": 1.7261940524371142e-7,
              "PriceInUSD": 0.000032833540501923115
            }
          }
        }
      ]
    }
  }
}